{
  "Iso": {
    "description": "Auto imported from components/Iso.vue"
  },
  "LazyIso": {
    "description": "Auto imported from components/Iso.vue"
  },
  "Isologo": {
    "description": "Auto imported from components/Isologo.vue"
  },
  "LazyIsologo": {
    "description": "Auto imported from components/Isologo.vue"
  },
  "ModeToggler": {
    "description": "Auto imported from components/ModeToggler.vue"
  },
  "LazyModeToggler": {
    "description": "Auto imported from components/ModeToggler.vue"
  }
}
